cavedb/__init__.py
cavedb/entity.py
cavedb/session.py
cavedb-1.0.1.dist-info/licenses/LICENSE
cavedb-1.0.1.dist-info/METADATA
cavedb-1.0.1.dist-info/WHEEL
cavedb-1.0.1.dist-info/top_level.txt
cavedb-1.0.1.dist-info/RECORD
