Metadata-Version: 2.4
Name: cavedb
Version: 1.0.1
Summary: Async JSONL-based database with ORM bindings to Python dataclasses
Author-email: Nikita Belomestnykh <medbeebs@gmail.com>
License-Expression: MIT
Project-URL: Homepage, https://github.com/medbeebs/cavedb
Project-URL: Repository, https://github.com/medbeebs/cavedb
Project-URL: Issues, https://github.com/medbeebs/hump/cavedb
Classifier: Operating System :: OS Independent
Classifier: Programming Language :: Python :: 3
Classifier: Programming Language :: Python
Classifier: Topic :: Software Development :: Libraries :: Application Frameworks
Classifier: Topic :: Software Development :: Libraries :: Python Modules
Classifier: Topic :: Software Development :: Libraries
Classifier: Topic :: Software Development
Classifier: Typing :: Typed
Classifier: Development Status :: 4 - Beta
Classifier: Intended Audience :: Developers
Classifier: Framework :: AsyncIO
Classifier: Programming Language :: Python
Classifier: Programming Language :: Python :: 3 :: Only
Classifier: Programming Language :: Python :: 3.13
Classifier: Programming Language :: Python :: 3.14
Classifier: Topic :: Database :: Front-Ends
Requires-Python: >=3.13
License-File: LICENSE
Requires-Dist: aiofiles>=25.1.0
Requires-Dist: orjson>=3.11.3
Dynamic: license-file
